[{"content":"","date":"15 April 2025","externalUrl":null,"permalink":"/tags/linh-tinh/","section":"Tags","summary":"","title":"Linh Tinh","type":"tags"},{"content":"The opening post for this blog. Obviously.\nThis isn’t my first time blogging, but because I’m lazy and bad at writing, I usually give up after one or two posts. Lately I’ve wanted to build a few things in my free time, so I’m writing to stay motivated. Oh right, I forgot to introduce myself — I do \u0026ldquo;the king of all jobs\u0026rdquo;, programming, so the title of this post is inspired by the first lesson every developer learns. It’s a bit boring, but… whatever, I suck at writing anyway. Plus, who’s even gonna read this 😂? Mostly I just need something to kick things off and make it feel less empty.\nAlright, that’s it for the intro. Hopefully the next posts (if this blog doesn’t die young like the previous ones 😅) will be better. See you around.\n","date":"15 April 2025","externalUrl":null,"permalink":"/en/random-stuff/hello-world/","section":"Random stuff","summary":"","title":"Hello world","type":"random-stuff"},{"content":"","date":"15 April 2025","externalUrl":null,"permalink":"/en/","section":"Lơ lửng","summary":"","title":"Lơ lửng","type":"page"},{"content":"","date":"15 April 2025","externalUrl":null,"permalink":"/en/tags/misc/","section":"Tags","summary":"","title":"Misc","type":"tags"},{"content":"","date":"15 April 2025","externalUrl":null,"permalink":"/en/random-stuff/","section":"Random stuff","summary":"","title":"Random stuff","type":"random-stuff"},{"content":"","date":"15 April 2025","externalUrl":null,"permalink":"/en/tags/","section":"Tags","summary":"","title":"Tags","type":"tags"},{"content":"","externalUrl":null,"permalink":"/en/series/","section":"Series","summary":"","title":"Series","type":"series"},{"content":"","externalUrl":null,"permalink":"/en/work/","section":"Work","summary":"","title":"Work","type":"work"}]